tyclonie_logger/__init__.py
Tyclonie_Logger-1.0.dist-info/METADATA
Tyclonie_Logger-1.0.dist-info/WHEEL
Tyclonie_Logger-1.0.dist-info/top_level.txt
Tyclonie_Logger-1.0.dist-info/RECORD
